<?xml version="1.0" encoding="UTF-8"?>

<!-- generated on 2022-02-02 13:38:43 by Eclipse SUMO sumo Version 1.10.0
<configuration xmlns:xsi="http://www.w3.org/2001/XMLSchema-instance" xsi:noNamespaceSchemaLocation="http://sumo.dlr.de/xsd/sumoConfiguration.xsd">

    <input>
        <net-file value="C:\Users\Marcus\Desktop\Hauptordner\Studium\Masterstudium\3.%20Semester\Projekt_Sim-Opt\Traffic_Simulation\arterial\arterialnet.net.xml"/>
        <route-files value="C:\Users\Marcus\Desktop\Hauptordner\Studium\Masterstudium\3.%20Semester\Projekt_Sim-Opt\Traffic_Simulation\arterial\arterialRoutes.xml"/>
        <additional-files value="C:\Users\Marcus\Desktop\Hauptordner\Studium\Masterstudium\3.%20Semester\Projekt_Sim-Opt\Traffic_Simulation\arterial\additionals.xml"/>
    </input>

    <output>
        <tripinfo-output value="../tripinfo.xml"/>
        <statistic-output value="../statistics.xml"/>
    </output>

    <report>
        <no-step-log value="true"/>
    </report>

    <traci_server>
        <remote-port value="65431"/>
    </traci_server>

</configuration>
-->

<detector xmlns:xsi="http://www.w3.org/2001/XMLSchema-instance" xsi:noNamespaceSchemaLocation="http://sumo.dlr.de/xsd/det_e2_file.xsd">
   <interval begin="0.00" end="300.00" id="detnDe" sampledSeconds="54.87" nVehEntered="9" nVehLeft="9" nVehSeen="9" meanSpeed="3.12" meanTimeLoss="4.20" meanOccupancy="5.64" maxOccupancy="59.64" meanMaxJamLengthInVehicles="0.08" meanMaxJamLengthInMeters="0.42" maxJamLengthInVehicles="1" maxJamLengthInMeters="5.00" jamLengthInVehiclesSum="25" jamLengthInMetersSum="125.00" meanHaltingDuration="9.33" maxHaltingDuration="14.00" haltingDurationSum="28.00" meanIntervalHaltingDuration="9.33" maxIntervalHaltingDuration="14.00" intervalHaltingDurationSum="28.00" startedHalts="3.00" meanVehicleNumber="0.21" maxVehicleNumber="2" />
   <interval begin="300.00" end="600.00" id="detnDe" sampledSeconds="116.68" nVehEntered="4" nVehLeft="4" nVehSeen="4" meanSpeed="0.65" meanTimeLoss="27.27" meanOccupancy="13.47" maxOccupancy="71.43" meanMaxJamLengthInVehicles="0.32" meanMaxJamLengthInMeters="1.62" maxJamLengthInVehicles="2" maxJamLengthInMeters="12.65" jamLengthInVehiclesSum="96" jamLengthInMetersSum="484.85" meanHaltingDuration="25.00" maxHaltingDuration="51.00" haltingDurationSum="100.00" meanIntervalHaltingDuration="25.00" maxIntervalHaltingDuration="51.00" intervalHaltingDurationSum="100.00" startedHalts="4.00" meanVehicleNumber="0.41" maxVehicleNumber="2" />
   <interval begin="600.00" end="900.00" id="detnDe" sampledSeconds="206.89" nVehEntered="9" nVehLeft="8" nVehSeen="9" meanSpeed="0.80" meanTimeLoss="21.15" meanOccupancy="23.98" maxOccupancy="71.43" meanMaxJamLengthInVehicles="0.58" meanMaxJamLengthInMeters="3.25" maxJamLengthInVehicles="2" maxJamLengthInMeters="12.62" jamLengthInVehiclesSum="173" jamLengthInMetersSum="975.32" meanHaltingDuration="29.83" maxHaltingDuration="58.00" haltingDurationSum="179.00" meanIntervalHaltingDuration="29.83" maxIntervalHaltingDuration="58.00" intervalHaltingDurationSum="179.00" startedHalts="6.00" meanVehicleNumber="0.72" maxVehicleNumber="2" />
   <interval begin="900.00" end="1200.00" id="detnDe" sampledSeconds="264.90" nVehEntered="5" nVehLeft="6" nVehSeen="6" meanSpeed="0.38" meanTimeLoss="42.47" meanOccupancy="30.84" maxOccupancy="71.43" meanMaxJamLengthInVehicles="0.80" meanMaxJamLengthInMeters="4.87" maxJamLengthInVehicles="2" maxJamLengthInMeters="13.50" jamLengthInVehiclesSum="240" jamLengthInMetersSum="1461.16" meanHaltingDuration="51.80" maxHaltingDuration="108.00" haltingDurationSum="259.00" meanIntervalHaltingDuration="48.80" maxIntervalHaltingDuration="108.00" intervalHaltingDurationSum="244.00" startedHalts="4.00" meanVehicleNumber="0.90" maxVehicleNumber="2" />
   <interval begin="1200.00" end="1500.00" id="detnDe" sampledSeconds="41.42" nVehEntered="6" nVehLeft="6" nVehSeen="6" meanSpeed="2.75" meanTimeLoss="5.00" meanOccupancy="4.45" maxOccupancy="35.71" meanMaxJamLengthInVehicles="0.07" meanMaxJamLengthInMeters="0.33" maxJamLengthInVehicles="1" maxJamLengthInMeters="5.00" jamLengthInVehiclesSum="20" jamLengthInMetersSum="100.00" meanHaltingDuration="7.67" maxHaltingDuration="11.00" haltingDurationSum="23.00" meanIntervalHaltingDuration="7.67" maxIntervalHaltingDuration="11.00" intervalHaltingDurationSum="23.00" startedHalts="3.00" meanVehicleNumber="0.16" maxVehicleNumber="1" />
   <interval begin="1500.00" end="1800.00" id="detnDe" sampledSeconds="247.50" nVehEntered="9" nVehLeft="8" nVehSeen="9" meanSpeed="0.67" meanTimeLoss="25.67" meanOccupancy="28.79" maxOccupancy="71.43" meanMaxJamLengthInVehicles="0.72" meanMaxJamLengthInMeters="4.21" maxJamLengthInVehicles="2" maxJamLengthInMeters="12.50" jamLengthInVehiclesSum="217" jamLengthInMetersSum="1262.58" meanHaltingDuration="55.25" maxHaltingDuration="108.00" haltingDurationSum="221.00" meanIntervalHaltingDuration="55.25" maxIntervalHaltingDuration="108.00" intervalHaltingDurationSum="221.00" startedHalts="4.00" meanVehicleNumber="0.86" maxVehicleNumber="2" />
   <interval begin="1800.00" end="2100.00" id="detnDe" sampledSeconds="132.86" nVehEntered="2" nVehLeft="3" nVehSeen="3" meanSpeed="0.33" meanTimeLoss="42.82" meanOccupancy="15.49" maxOccupancy="35.71" meanMaxJamLengthInVehicles="0.40" meanMaxJamLengthInMeters="2.02" maxJamLengthInVehicles="1" maxJamLengthInMeters="5.00" jamLengthInVehiclesSum="121" jamLengthInMetersSum="604.69" meanHaltingDuration="41.67" maxHaltingDuration="56.00" haltingDurationSum="125.00" meanIntervalHaltingDuration="41.00" maxIntervalHaltingDuration="54.00" intervalHaltingDurationSum="123.00" startedHalts="2.00" meanVehicleNumber="0.45" maxVehicleNumber="1" />
   <interval begin="2100.00" end="2400.00" id="detnDe" sampledSeconds="212.57" nVehEntered="8" nVehLeft="6" nVehSeen="8" meanSpeed="0.62" meanTimeLoss="24.91" meanOccupancy="24.70" maxOccupancy="71.43" meanMaxJamLengthInVehicles="0.59" meanMaxJamLengthInMeters="3.42" maxJamLengthInVehicles="2" maxJamLengthInMeters="12.78" jamLengthInVehiclesSum="176" jamLengthInMetersSum="1025.79" meanHaltingDuration="26.14" maxHaltingDuration="61.00" haltingDurationSum="183.00" meanIntervalHaltingDuration="26.14" maxIntervalHaltingDuration="61.00" intervalHaltingDurationSum="183.00" startedHalts="7.00" meanVehicleNumber="0.73" maxVehicleNumber="2" />
   <interval begin="2400.00" end="2700.00" id="detnDe" sampledSeconds="87.53" nVehEntered="3" nVehLeft="4" nVehSeen="5" meanSpeed="0.81" meanTimeLoss="16.10" meanOccupancy="10.00" maxOccupancy="71.43" meanMaxJamLengthInVehicles="0.24" meanMaxJamLengthInMeters="1.42" maxJamLengthInVehicles="2" maxJamLengthInMeters="12.50" jamLengthInVehiclesSum="73" jamLengthInMetersSum="425.03" meanHaltingDuration="34.25" maxHaltingDuration="63.00" haltingDurationSum="137.00" meanIntervalHaltingDuration="18.75" maxIntervalHaltingDuration="26.00" intervalHaltingDurationSum="75.00" startedHalts="2.00" meanVehicleNumber="0.30" maxVehicleNumber="2" />
   <interval begin="2700.00" end="3000.00" id="detnDe" sampledSeconds="240.55" nVehEntered="6" nVehLeft="7" nVehSeen="7" meanSpeed="0.50" meanTimeLoss="32.65" meanOccupancy="27.80" maxOccupancy="71.43" meanMaxJamLengthInVehicles="0.70" meanMaxJamLengthInMeters="3.78" maxJamLengthInVehicles="2" maxJamLengthInMeters="12.53" jamLengthInVehiclesSum="211" jamLengthInMetersSum="1135.08" meanHaltingDuration="38.83" maxHaltingDuration="106.00" haltingDurationSum="233.00" meanIntervalHaltingDuration="36.00" maxIntervalHaltingDuration="106.00" intervalHaltingDurationSum="216.00" startedHalts="5.00" meanVehicleNumber="0.82" maxVehicleNumber="2" />
   <interval begin="3000.00" end="3300.00" id="detnDe" sampledSeconds="130.59" nVehEntered="2" nVehLeft="2" nVehSeen="2" meanSpeed="0.29" meanTimeLoss="63.40" meanOccupancy="15.34" maxOccupancy="35.71" meanMaxJamLengthInVehicles="0.40" meanMaxJamLengthInMeters="2.02" maxJamLengthInVehicles="1" maxJamLengthInMeters="5.00" jamLengthInVehiclesSum="121" jamLengthInMetersSum="605.00" meanHaltingDuration="61.50" maxHaltingDuration="106.00" haltingDurationSum="123.00" meanIntervalHaltingDuration="61.50" maxIntervalHaltingDuration="106.00" intervalHaltingDurationSum="123.00" startedHalts="2.00" meanVehicleNumber="0.44" maxVehicleNumber="1" />
   <interval begin="3300.00" end="3600.00" id="detnDe" sampledSeconds="383.90" nVehEntered="9" nVehLeft="9" nVehSeen="9" meanSpeed="0.45" meanTimeLoss="40.76" meanOccupancy="44.70" maxOccupancy="71.43" meanMaxJamLengthInVehicles="1.14" meanMaxJamLengthInMeters="6.81" maxJamLengthInVehicles="2" maxJamLengthInMeters="13.50" jamLengthInVehiclesSum="341" jamLengthInMetersSum="2043.72" meanHaltingDuration="49.71" maxHaltingDuration="89.00" haltingDurationSum="348.00" meanIntervalHaltingDuration="49.71" maxIntervalHaltingDuration="89.00" intervalHaltingDurationSum="348.00" startedHalts="7.00" meanVehicleNumber="1.32" maxVehicleNumber="2" />
   <interval begin="3600.00" end="3900.00" id="detnDe" sampledSeconds="42.69" nVehEntered="1" nVehLeft="1" nVehSeen="1" meanSpeed="0.45" meanTimeLoss="40.79" meanOccupancy="5.00" maxOccupancy="35.71" meanMaxJamLengthInVehicles="0.12" meanMaxJamLengthInMeters="0.62" maxJamLengthInVehicles="1" maxJamLengthInMeters="5.00" jamLengthInVehiclesSum="37" jamLengthInMetersSum="185.00" meanHaltingDuration="38.00" maxHaltingDuration="38.00" haltingDurationSum="38.00" meanIntervalHaltingDuration="38.00" maxIntervalHaltingDuration="38.00" intervalHaltingDurationSum="38.00" startedHalts="1.00" meanVehicleNumber="0.15" maxVehicleNumber="1" />
   <interval begin="3900.00" end="3977.00" id="detnDe" sampledSeconds="0.00" nVehEntered="0" nVehLeft="0" nVehSeen="0" meanSpeed="-1.00" meanTimeLoss="-1.00" meanOccupancy="0.00" maxOccupancy="0.00" meanMaxJamLengthInVehicles="0.00" meanMaxJamLengthInMeters="0.00" maxJamLengthInVehicles="0" maxJamLengthInMeters="0.00" jamLengthInVehiclesSum="0" jamLengthInMetersSum="0.00" meanHaltingDuration="0.00" maxHaltingDuration="0.00" haltingDurationSum="0.00" meanIntervalHaltingDuration="0.00" maxIntervalHaltingDuration="0.00" intervalHaltingDurationSum="0.00" startedHalts="0.00" meanVehicleNumber="0.00" maxVehicleNumber="0" />
</detector>
